spaim/__init__.py
spaim/classifiers.py
spaim/filters.py
spaim/injection.py
spaim/message.py
spaim/prompt.py
spaim/tools.py
spaim-0.1.0.dist-info/licenses/LICENSE
spaim-0.1.0.dist-info/METADATA
spaim-0.1.0.dist-info/WHEEL
spaim-0.1.0.dist-info/top_level.txt
spaim-0.1.0.dist-info/RECORD
