Metadata-Version: 2.4
Name: spaim
Version: 0.1.0
Summary: A library to test prompt injections on large language models.
Author-email: Kyle Vachon <fief_toe.9x@icloud.com>
Project-URL: Homepage, https://github.com/kv-cash/spaim
Project-URL: Issues, https://github.com/kv-cash/spaim/issues
Classifier: Programming Language :: Python :: 3
Classifier: License :: OSI Approved :: MIT License
Classifier: Operating System :: OS Independent
Requires-Python: >=3.9
License-File: LICENSE
Requires-Dist: transformers>=4.55.0
Dynamic: license-file
